<?xml version="1.0"?>
<?mso-application progid="Excel.Sheet"?>
<Workbook xmlns="urn:schemas-microsoft-com:office:spreadsheet"
 xmlns:o="urn:schemas-microsoft-com:office:office"
 xmlns:x="urn:schemas-microsoft-com:office:excel"
 xmlns:ss="urn:schemas-microsoft-com:office:spreadsheet"
 xmlns:html="http://www.w3.org/TR/REC-html40">
 <DocumentProperties xmlns="urn:schemas-microsoft-com:office:office">
  <Author>Microsiga Protheus</Author>
  <LastAuthor>Leandro Ventrilho</LastAuthor>
  <Created>2011-11-11T00:00:00Z</Created>
  <Version>16.00</Version>
 </DocumentProperties>
 <OfficeDocumentSettings xmlns="urn:schemas-microsoft-com:office:office">
  <AllowPNG/>
 </OfficeDocumentSettings>
 <ExcelWorkbook xmlns="urn:schemas-microsoft-com:office:excel">
  <WindowHeight>7020</WindowHeight>
  <WindowWidth>17730</WindowWidth>
  <WindowTopX>0</WindowTopX>
  <WindowTopY>0</WindowTopY>
  <ProtectStructure>False</ProtectStructure>
  <ProtectWindows>False</ProtectWindows>
 </ExcelWorkbook>
 <Styles>
  <Style ss:ID="Default" ss:Name="Normal">
   <Alignment ss:Vertical="Bottom"/>
   <Font ss:FontName="Calibri" x:Family="Swiss" ss:Size="11" ss:Color="#000000"/>
  </Style>
  <Style ss:ID="s65">
   <Alignment ss:Horizontal="Center" ss:Vertical="Bottom"/>
   <Borders>
    <Border ss:Position="Right" ss:LineStyle="Continuous" ss:Weight="1"
     ss:Color="#A01212"/>
    <Border ss:Position="Top" ss:LineStyle="Continuous" ss:Weight="1"
     ss:Color="#A01212"/>
   </Borders>
   <Font ss:FontName="Calibri" x:Family="Swiss" ss:Size="11" ss:Color="#FFFFFF"
    ss:Bold="1"/>
   <Interior ss:Color="#A01212" ss:Pattern="Solid"/>
  </Style>
  <Style ss:ID="s66">
   <Alignment ss:Horizontal="Center" ss:Vertical="Bottom"/>
   <Borders>
    <Border ss:Position="Left" ss:LineStyle="Continuous" ss:Weight="1"
     ss:Color="#DE7D7D"/>
    <Border ss:Position="Top" ss:LineStyle="Continuous" ss:Weight="1"
     ss:Color="#DE7D7D"/>
   </Borders>
   <Font ss:FontName="Calibri" x:Family="Swiss" ss:Size="11" ss:Color="#000000"/>
   <Interior ss:Color="#DE7D7D" ss:Pattern="Solid"/>
  </Style>
  <Style ss:ID="s67">
   <Alignment ss:Horizontal="Left" ss:Vertical="Bottom"/>
   <Borders>
    <Border ss:Position="Left" ss:LineStyle="Continuous" ss:Weight="1"
     ss:Color="#DE7D7D"/>
    <Border ss:Position="Top" ss:LineStyle="Continuous" ss:Weight="1"
     ss:Color="#DE7D7D"/>
   </Borders>
   <Font ss:FontName="Calibri" x:Family="Swiss" ss:Size="11" ss:Color="#000000"/>
   <Interior ss:Color="#DE7D7D" ss:Pattern="Solid"/>
  </Style>
  <Style ss:ID="s68">
   <Alignment ss:Horizontal="Center" ss:Vertical="Bottom"/>
   <Borders>
    <Border ss:Position="Left" ss:LineStyle="Continuous" ss:Weight="1"
     ss:Color="#DE7D7D"/>
    <Border ss:Position="Top" ss:LineStyle="Continuous" ss:Weight="1"
     ss:Color="#DE7D7D"/>
   </Borders>
   <Font ss:FontName="Calibri" x:Family="Swiss" ss:Size="11" ss:Color="#000000"/>
   <Interior ss:Color="#DE7D7D" ss:Pattern="Solid"/>
   <NumberFormat ss:Format="Short Date"/>
  </Style>
  <Style ss:ID="s69">
   <Alignment ss:Horizontal="Right" ss:Vertical="Bottom"/>
   <Borders>
    <Border ss:Position="Left" ss:LineStyle="Continuous" ss:Weight="1"
     ss:Color="#DE7D7D"/>
    <Border ss:Position="Top" ss:LineStyle="Continuous" ss:Weight="1"
     ss:Color="#DE7D7D"/>
   </Borders>
   <Font ss:FontName="Calibri" x:Family="Swiss" ss:Size="11" ss:Color="#000000"/>
   <Interior ss:Color="#DE7D7D" ss:Pattern="Solid"/>
  </Style>
  <Style ss:ID="s70">
   <Alignment ss:Horizontal="Center" ss:Vertical="Bottom"/>
   <Borders>
    <Border ss:Position="Left" ss:LineStyle="Continuous" ss:Weight="1"
     ss:Color="#ECAFAF"/>
    <Border ss:Position="Top" ss:LineStyle="Continuous" ss:Weight="1"
     ss:Color="#ECAFAF"/>
   </Borders>
   <Font ss:FontName="Calibri" x:Family="Swiss" ss:Size="11" ss:Color="#000000"/>
   <Interior ss:Color="#ECAFAF" ss:Pattern="Solid"/>
  </Style>
  <Style ss:ID="s71">
   <Alignment ss:Horizontal="Left" ss:Vertical="Bottom"/>
   <Borders>
    <Border ss:Position="Left" ss:LineStyle="Continuous" ss:Weight="1"
     ss:Color="#ECAFAF"/>
    <Border ss:Position="Top" ss:LineStyle="Continuous" ss:Weight="1"
     ss:Color="#ECAFAF"/>
   </Borders>
   <Font ss:FontName="Calibri" x:Family="Swiss" ss:Size="11" ss:Color="#000000"/>
   <Interior ss:Color="#ECAFAF" ss:Pattern="Solid"/>
  </Style>
  <Style ss:ID="s72">
   <Alignment ss:Horizontal="Center" ss:Vertical="Bottom"/>
   <Borders>
    <Border ss:Position="Left" ss:LineStyle="Continuous" ss:Weight="1"
     ss:Color="#ECAFAF"/>
    <Border ss:Position="Top" ss:LineStyle="Continuous" ss:Weight="1"
     ss:Color="#ECAFAF"/>
   </Borders>
   <Font ss:FontName="Calibri" x:Family="Swiss" ss:Size="11" ss:Color="#000000"/>
   <Interior ss:Color="#ECAFAF" ss:Pattern="Solid"/>
   <NumberFormat ss:Format="Short Date"/>
  </Style>
  <Style ss:ID="s73">
   <Alignment ss:Horizontal="Right" ss:Vertical="Bottom"/>
   <Borders>
    <Border ss:Position="Left" ss:LineStyle="Continuous" ss:Weight="1"
     ss:Color="#ECAFAF"/>
    <Border ss:Position="Top" ss:LineStyle="Continuous" ss:Weight="1"
     ss:Color="#ECAFAF"/>
   </Borders>
   <Font ss:FontName="Calibri" x:Family="Swiss" ss:Size="11" ss:Color="#000000"/>
   <Interior ss:Color="#ECAFAF" ss:Pattern="Solid"/>
  </Style>
  <Style ss:ID="s74">
   <Alignment ss:Horizontal="Right" ss:Vertical="Bottom"/>
   <Borders>
    <Border ss:Position="Left" ss:LineStyle="Continuous" ss:Weight="1"
     ss:Color="#DE7D7D"/>
    <Border ss:Position="Top" ss:LineStyle="Continuous" ss:Weight="1"
     ss:Color="#DE7D7D"/>
   </Borders>
   <Font ss:FontName="Calibri" x:Family="Swiss" ss:Size="11" ss:Color="#000000"/>
   <Interior ss:Color="#DE7D7D" ss:Pattern="Solid"/>
   <NumberFormat/>
  </Style>
  <Style ss:ID="s75">
   <Alignment ss:Horizontal="Right" ss:Vertical="Bottom"/>
   <Borders>
    <Border ss:Position="Left" ss:LineStyle="Continuous" ss:Weight="1"
     ss:Color="#ECAFAF"/>
    <Border ss:Position="Top" ss:LineStyle="Continuous" ss:Weight="1"
     ss:Color="#ECAFAF"/>
   </Borders>
   <Font ss:FontName="Calibri" x:Family="Swiss" ss:Size="11" ss:Color="#000000"/>
   <Interior ss:Color="#ECAFAF" ss:Pattern="Solid"/>
   <NumberFormat/>
  </Style>
  <Style ss:ID="s76">
   <Alignment ss:Horizontal="Right" ss:Vertical="Bottom"/>
   <Borders>
    <Border ss:Position="Left" ss:LineStyle="Continuous" ss:Weight="1"
     ss:Color="#DE7D7D"/>
    <Border ss:Position="Top" ss:LineStyle="Continuous" ss:Weight="1"
     ss:Color="#DE7D7D"/>
   </Borders>
   <Font ss:FontName="Calibri" x:Family="Swiss" ss:Size="11" ss:Color="#000000"/>
   <Interior ss:Color="#DE7D7D" ss:Pattern="Solid"/>
   <NumberFormat ss:Format="#,##0"/>
  </Style>
  <Style ss:ID="s77">
   <Alignment ss:Horizontal="Right" ss:Vertical="Bottom"/>
   <Borders>
    <Border ss:Position="Left" ss:LineStyle="Continuous" ss:Weight="1"
     ss:Color="#ECAFAF"/>
    <Border ss:Position="Top" ss:LineStyle="Continuous" ss:Weight="1"
     ss:Color="#ECAFAF"/>
   </Borders>
   <Font ss:FontName="Calibri" x:Family="Swiss" ss:Size="11" ss:Color="#000000"/>
   <Interior ss:Color="#ECAFAF" ss:Pattern="Solid"/>
   <NumberFormat ss:Format="#,##0"/>
  </Style>
  <Style ss:ID="s134">
   <Alignment ss:Horizontal="Center" ss:Vertical="Bottom"/>
   <Borders>
    <Border ss:Position="Left" ss:LineStyle="Continuous" ss:Weight="1"
     ss:Color="#ECAFAF"/>
    <Border ss:Position="Top" ss:LineStyle="Continuous" ss:Weight="1"
     ss:Color="#ECAFAF"/>
   </Borders>
   <Font ss:FontName="Calibri" x:Family="Swiss" ss:Size="11" ss:Color="#000000"/>
   <Interior ss:Color="#FFFF00" ss:Pattern="Solid"/>
  </Style>
  <Style ss:ID="s135">
   <Alignment ss:Horizontal="Left" ss:Vertical="Bottom"/>
   <Borders>
    <Border ss:Position="Left" ss:LineStyle="Continuous" ss:Weight="1"
     ss:Color="#ECAFAF"/>
    <Border ss:Position="Top" ss:LineStyle="Continuous" ss:Weight="1"
     ss:Color="#ECAFAF"/>
   </Borders>
   <Font ss:FontName="Calibri" x:Family="Swiss" ss:Size="11" ss:Color="#000000"/>
   <Interior ss:Color="#FFFF00" ss:Pattern="Solid"/>
  </Style>
  <Style ss:ID="s136">
   <Alignment ss:Horizontal="Center" ss:Vertical="Bottom"/>
   <Borders>
    <Border ss:Position="Left" ss:LineStyle="Continuous" ss:Weight="1"
     ss:Color="#ECAFAF"/>
    <Border ss:Position="Top" ss:LineStyle="Continuous" ss:Weight="1"
     ss:Color="#ECAFAF"/>
   </Borders>
   <Font ss:FontName="Calibri" x:Family="Swiss" ss:Size="11" ss:Color="#000000"/>
   <Interior ss:Color="#FFFF00" ss:Pattern="Solid"/>
   <NumberFormat ss:Format="Short Date"/>
  </Style>
  <Style ss:ID="s137">
   <Alignment ss:Horizontal="Right" ss:Vertical="Bottom"/>
   <Borders>
    <Border ss:Position="Left" ss:LineStyle="Continuous" ss:Weight="1"
     ss:Color="#ECAFAF"/>
    <Border ss:Position="Top" ss:LineStyle="Continuous" ss:Weight="1"
     ss:Color="#ECAFAF"/>
   </Borders>
   <Font ss:FontName="Calibri" x:Family="Swiss" ss:Size="11" ss:Color="#000000"/>
   <Interior ss:Color="#FFFF00" ss:Pattern="Solid"/>
   <NumberFormat/>
  </Style>
  <Style ss:ID="s138">
   <Alignment ss:Horizontal="Right" ss:Vertical="Bottom"/>
   <Borders>
    <Border ss:Position="Left" ss:LineStyle="Continuous" ss:Weight="1"
     ss:Color="#ECAFAF"/>
    <Border ss:Position="Top" ss:LineStyle="Continuous" ss:Weight="1"
     ss:Color="#ECAFAF"/>
   </Borders>
   <Font ss:FontName="Calibri" x:Family="Swiss" ss:Size="11" ss:Color="#000000"/>
   <Interior ss:Color="#FFFF00" ss:Pattern="Solid"/>
  </Style>
  <Style ss:ID="s140">
   <Alignment ss:Horizontal="Center" ss:Vertical="Bottom"/>
   <Borders>
    <Border ss:Position="Left" ss:LineStyle="Continuous" ss:Weight="1"
     ss:Color="#DE7D7D"/>
    <Border ss:Position="Top" ss:LineStyle="Continuous" ss:Weight="1"
     ss:Color="#DE7D7D"/>
   </Borders>
   <Font ss:FontName="Calibri" x:Family="Swiss" ss:Size="11" ss:Color="#000000"/>
   <Interior ss:Color="#FFFF00" ss:Pattern="Solid"/>
  </Style>
  <Style ss:ID="s141">
   <Alignment ss:Horizontal="Left" ss:Vertical="Bottom"/>
   <Borders>
    <Border ss:Position="Left" ss:LineStyle="Continuous" ss:Weight="1"
     ss:Color="#DE7D7D"/>
    <Border ss:Position="Top" ss:LineStyle="Continuous" ss:Weight="1"
     ss:Color="#DE7D7D"/>
   </Borders>
   <Font ss:FontName="Calibri" x:Family="Swiss" ss:Size="11" ss:Color="#000000"/>
   <Interior ss:Color="#FFFF00" ss:Pattern="Solid"/>
  </Style>
  <Style ss:ID="s142">
   <Alignment ss:Horizontal="Center" ss:Vertical="Bottom"/>
   <Borders>
    <Border ss:Position="Left" ss:LineStyle="Continuous" ss:Weight="1"
     ss:Color="#DE7D7D"/>
    <Border ss:Position="Top" ss:LineStyle="Continuous" ss:Weight="1"
     ss:Color="#DE7D7D"/>
   </Borders>
   <Font ss:FontName="Calibri" x:Family="Swiss" ss:Size="11" ss:Color="#000000"/>
   <Interior ss:Color="#FFFF00" ss:Pattern="Solid"/>
   <NumberFormat ss:Format="Short Date"/>
  </Style>
  <Style ss:ID="s143">
   <Alignment ss:Horizontal="Right" ss:Vertical="Bottom"/>
   <Borders>
    <Border ss:Position="Left" ss:LineStyle="Continuous" ss:Weight="1"
     ss:Color="#DE7D7D"/>
    <Border ss:Position="Top" ss:LineStyle="Continuous" ss:Weight="1"
     ss:Color="#DE7D7D"/>
   </Borders>
   <Font ss:FontName="Calibri" x:Family="Swiss" ss:Size="11" ss:Color="#000000"/>
   <Interior ss:Color="#FFFF00" ss:Pattern="Solid"/>
   <NumberFormat/>
  </Style>
  <Style ss:ID="s144">
   <Alignment ss:Horizontal="Right" ss:Vertical="Bottom"/>
   <Borders>
    <Border ss:Position="Left" ss:LineStyle="Continuous" ss:Weight="1"
     ss:Color="#DE7D7D"/>
    <Border ss:Position="Top" ss:LineStyle="Continuous" ss:Weight="1"
     ss:Color="#DE7D7D"/>
   </Borders>
   <Font ss:FontName="Calibri" x:Family="Swiss" ss:Size="11" ss:Color="#000000"/>
   <Interior ss:Color="#FFFF00" ss:Pattern="Solid"/>
  </Style>
 </Styles>
 <Worksheet ss:Name="1-Plan1">
  <Names>
   <NamedRange ss:Name="_FilterDatabase" ss:RefersTo="='1-Plan1'!R1C1:R18C22"
    ss:Hidden="1"/>
  </Names>
  <Table ss:ExpandedColumnCount="22" ss:ExpandedRowCount="14" x:FullColumns="1"
   x:FullRows="1" ss:DefaultRowHeight="15">
   <Column ss:Width="72.75"/>
   <Column ss:Width="85.5"/>
   <Column ss:Width="264"/>
   <Column ss:Width="39.75"/>
   <Column ss:Width="72.75"/>
   <Column ss:Width="52.5"/>
   <Column ss:Width="79.5"/>
   <Column ss:Width="336.75"/>
   <Column ss:Width="151.5"/>
   <Column ss:Width="52.5"/>
   <Column ss:Width="92.25"/>
   <Column ss:Width="13.5"/>
   <Column ss:Width="198"/>
   <Column ss:Width="99"/>
   <Column ss:Width="66"/>
   <Column ss:Width="99"/>
   <Column ss:Width="561"/>
   <Column ss:Width="59.25"/>
   <Column ss:Width="46.5"/>
   <Column ss:Width="99"/>
   <Column ss:Width="39.75"/>
   <Column ss:Width="33"/>
   <Row ss:AutoFitHeight="0">
    <Cell ss:StyleID="s65"><Data ss:Type="String">Lj Embarque</Data><NamedCell
      ss:Name="_FilterDatabase"/></Cell>
    <Cell ss:StyleID="s65"><Data ss:Type="String">Cod. Vendedor</Data><NamedCell
      ss:Name="_FilterDatabase"/></Cell>
    <Cell ss:StyleID="s65"><Data ss:Type="String">Vendedor</Data><NamedCell
      ss:Name="_FilterDatabase"/></Cell>
    <Cell ss:StyleID="s65"><Data ss:Type="String">Pedido</Data><NamedCell
      ss:Name="_FilterDatabase"/></Cell>
    <Cell ss:StyleID="s65"><Data ss:Type="String">Data Pedido</Data><NamedCell
      ss:Name="_FilterDatabase"/></Cell>
    <Cell ss:StyleID="s65"><Data ss:Type="String">Liberado</Data><NamedCell
      ss:Name="_FilterDatabase"/></Cell>
    <Cell ss:StyleID="s65"><Data ss:Type="String">Cliente/Loja</Data><NamedCell
      ss:Name="_FilterDatabase"/></Cell>
    <Cell ss:StyleID="s65"><Data ss:Type="String">Razao Social</Data><NamedCell
      ss:Name="_FilterDatabase"/></Cell>
    <Cell ss:StyleID="s65"><Data ss:Type="String">Bairro</Data><NamedCell
      ss:Name="_FilterDatabase"/></Cell>
    <Cell ss:StyleID="s65"><Data ss:Type="String">CEP</Data><NamedCell
      ss:Name="_FilterDatabase"/></Cell>
    <Cell ss:StyleID="s65"><Data ss:Type="String">Cidade</Data><NamedCell
      ss:Name="_FilterDatabase"/></Cell>
    <Cell ss:StyleID="s65"><Data ss:Type="String">UF</Data><NamedCell
      ss:Name="_FilterDatabase"/></Cell>
    <Cell ss:StyleID="s65"><Data ss:Type="String">Obs. Pedido</Data><NamedCell
      ss:Name="_FilterDatabase"/></Cell>
    <Cell ss:StyleID="s65"><Data ss:Type="String">Dt Carregamento</Data><NamedCell
      ss:Name="_FilterDatabase"/></Cell>
    <Cell ss:StyleID="s65"><Data ss:Type="String">Dt Entrega</Data><NamedCell
      ss:Name="_FilterDatabase"/></Cell>
    <Cell ss:StyleID="s65"><Data ss:Type="String">Cod. Produto</Data><NamedCell
      ss:Name="_FilterDatabase"/></Cell>
    <Cell ss:StyleID="s65"><Data ss:Type="String">Produto</Data><NamedCell
      ss:Name="_FilterDatabase"/></Cell>
    <Cell ss:StyleID="s65"><Data ss:Type="String">Qtd Total</Data><NamedCell
      ss:Name="_FilterDatabase"/></Cell>
    <Cell ss:StyleID="s65"><Data ss:Type="String">Peso Cx</Data><NamedCell
      ss:Name="_FilterDatabase"/></Cell>
    <Cell ss:StyleID="s65"><Data ss:Type="String">Vl Total Pedido</Data><NamedCell
      ss:Name="_FilterDatabase"/></Cell>
    <Cell ss:StyleID="s65"><Data ss:Type="String">Viagem</Data><NamedCell
      ss:Name="_FilterDatabase"/></Cell>
    <Cell ss:StyleID="s65"><Data ss:Type="String">Carga</Data><NamedCell
      ss:Name="_FilterDatabase"/></Cell>
   </Row>
   <Row ss:AutoFitHeight="0">
    <Cell ss:StyleID="s66"><Data ss:Type="String">51</Data><NamedCell
      ss:Name="_FilterDatabase"/></Cell>
    <Cell ss:StyleID="s67"><Data ss:Type="String">000050</Data><NamedCell
      ss:Name="_FilterDatabase"/></Cell>
    <Cell ss:StyleID="s67"><Data ss:Type="String">SARTORATO REPRESENTACOES COMERCIAIS LTDA</Data><NamedCell
      ss:Name="_FilterDatabase"/></Cell>
    <Cell ss:StyleID="s66"><Data ss:Type="String">027438</Data><NamedCell
      ss:Name="_FilterDatabase"/></Cell>
    <Cell ss:StyleID="s68"><Data ss:Type="DateTime">2023-07-27T00:00:00.000</Data><NamedCell
      ss:Name="_FilterDatabase"/></Cell>
    <Cell ss:StyleID="s66"><Data ss:Type="String">Sim</Data><NamedCell
      ss:Name="_FilterDatabase"/></Cell>
    <Cell ss:StyleID="s66"><Data ss:Type="String">005417/01</Data><NamedCell
      ss:Name="_FilterDatabase"/></Cell>
    <Cell ss:StyleID="s67"><Data ss:Type="String">FERNANDO PALMIERI &amp; CIA LTDA</Data><NamedCell
      ss:Name="_FilterDatabase"/></Cell>
    <Cell ss:StyleID="s67"><Data ss:Type="String">CENTRO</Data><NamedCell
      ss:Name="_FilterDatabase"/></Cell>
    <Cell ss:StyleID="s67"><Data ss:Type="String">14580000</Data><NamedCell
      ss:Name="_FilterDatabase"/></Cell>
    <Cell ss:StyleID="s67"><Data ss:Type="String">GUARA</Data><NamedCell
      ss:Name="_FilterDatabase"/></Cell>
    <Cell ss:StyleID="s66"><Data ss:Type="String">SP</Data><NamedCell
      ss:Name="_FilterDatabase"/></Cell>
    <Cell ss:StyleID="s67"><Data ss:Type="String"></Data><NamedCell
      ss:Name="_FilterDatabase"/></Cell>
    <Cell ss:StyleID="s68"><Data ss:Type="DateTime">2023-07-30T00:00:00.000</Data><NamedCell
      ss:Name="_FilterDatabase"/></Cell>
    <Cell ss:StyleID="s68"><Data ss:Type="DateTime">2023-07-31T00:00:00.000</Data><NamedCell
      ss:Name="_FilterDatabase"/></Cell>
    <Cell ss:StyleID="s66"><Data ss:Type="String">FRCSMIFMI000001</Data><NamedCell
      ss:Name="_FilterDatabase"/></Cell>
    <Cell ss:StyleID="s67"><Data ss:Type="String">CORTES CONGELADOS DE FRANGO (COXA E SOBRECOXA INDIVID) CX PP 18 KG MISTER FRANGO</Data><NamedCell
      ss:Name="_FilterDatabase"/></Cell>
    <Cell ss:StyleID="s74"><Data ss:Type="Number">720</Data><NamedCell
      ss:Name="_FilterDatabase"/></Cell>
    <Cell ss:StyleID="s69"><Data ss:Type="String">18</Data><NamedCell
      ss:Name="_FilterDatabase"/></Cell>
    <Cell ss:StyleID="s69"><Data ss:Type="String">4.032,00</Data><NamedCell
      ss:Name="_FilterDatabase"/></Cell>
    <Cell ss:StyleID="s66"><Data ss:Type="String"></Data><NamedCell
      ss:Name="_FilterDatabase"/></Cell>
    <Cell ss:StyleID="s66"><Data ss:Type="String"></Data><NamedCell
      ss:Name="_FilterDatabase"/></Cell>
   </Row>
   <Row ss:AutoFitHeight="0">
    <Cell ss:StyleID="s70"><Data ss:Type="String">51</Data><NamedCell
      ss:Name="_FilterDatabase"/></Cell>
    <Cell ss:StyleID="s71"><Data ss:Type="String">000043</Data><NamedCell
      ss:Name="_FilterDatabase"/></Cell>
    <Cell ss:StyleID="s71"><Data ss:Type="String">A. V. MARTINS REPRESENTACOES COMERCIAIS</Data><NamedCell
      ss:Name="_FilterDatabase"/></Cell>
    <Cell ss:StyleID="s70"><Data ss:Type="String">027447</Data><NamedCell
      ss:Name="_FilterDatabase"/></Cell>
    <Cell ss:StyleID="s72"><Data ss:Type="DateTime">2023-07-27T00:00:00.000</Data><NamedCell
      ss:Name="_FilterDatabase"/></Cell>
    <Cell ss:StyleID="s70"><Data ss:Type="String">Sim</Data><NamedCell
      ss:Name="_FilterDatabase"/></Cell>
    <Cell ss:StyleID="s70"><Data ss:Type="String">044944/02</Data><NamedCell
      ss:Name="_FilterDatabase"/></Cell>
    <Cell ss:StyleID="s71"><Data ss:Type="String">SUPERMERCADO CAPITELLI LTDA</Data><NamedCell
      ss:Name="_FilterDatabase"/></Cell>
    <Cell ss:StyleID="s71"><Data ss:Type="String">JD BOA VISTA</Data><NamedCell
      ss:Name="_FilterDatabase"/></Cell>
    <Cell ss:StyleID="s71"><Data ss:Type="String">14150000</Data><NamedCell
      ss:Name="_FilterDatabase"/></Cell>
    <Cell ss:StyleID="s71"><Data ss:Type="String">SERRANA</Data><NamedCell
      ss:Name="_FilterDatabase"/></Cell>
    <Cell ss:StyleID="s70"><Data ss:Type="String">SP</Data><NamedCell
      ss:Name="_FilterDatabase"/></Cell>
    <Cell ss:StyleID="s71"><Data ss:Type="String"></Data><NamedCell
      ss:Name="_FilterDatabase"/></Cell>
    <Cell ss:StyleID="s72"><Data ss:Type="DateTime">2023-07-30T00:00:00.000</Data><NamedCell
      ss:Name="_FilterDatabase"/></Cell>
    <Cell ss:StyleID="s72"><Data ss:Type="DateTime">2023-07-31T00:00:00.000</Data><NamedCell
      ss:Name="_FilterDatabase"/></Cell>
    <Cell ss:StyleID="s70"><Data ss:Type="String">FRPTCANMI000033</Data><NamedCell
      ss:Name="_FilterDatabase"/></Cell>
    <Cell ss:StyleID="s71"><Data ss:Type="String">CORTES CONGELADOS DE FRANGO (FILE DE PEITO INDIVIDUAL) CX PP 20 KG (CANCAO ALIMENTOS)</Data><NamedCell
      ss:Name="_FilterDatabase"/></Cell>
    <Cell ss:StyleID="s75"><Data ss:Type="Number">300</Data><NamedCell
      ss:Name="_FilterDatabase"/></Cell>
    <Cell ss:StyleID="s73"><Data ss:Type="String">20</Data><NamedCell
      ss:Name="_FilterDatabase"/></Cell>
    <Cell ss:StyleID="s73"><Data ss:Type="String">2.820,00</Data><NamedCell
      ss:Name="_FilterDatabase"/></Cell>
    <Cell ss:StyleID="s70"><Data ss:Type="String"></Data><NamedCell
      ss:Name="_FilterDatabase"/></Cell>
    <Cell ss:StyleID="s70"><Data ss:Type="String"></Data><NamedCell
      ss:Name="_FilterDatabase"/></Cell>
   </Row>
   <Row ss:AutoFitHeight="0">
    <Cell ss:StyleID="s66"><Data ss:Type="String">51</Data><NamedCell
      ss:Name="_FilterDatabase"/></Cell>
    <Cell ss:StyleID="s67"><Data ss:Type="String">000043</Data><NamedCell
      ss:Name="_FilterDatabase"/></Cell>
    <Cell ss:StyleID="s67"><Data ss:Type="String">A. V. MARTINS REPRESENTACOES COMERCIAIS</Data><NamedCell
      ss:Name="_FilterDatabase"/></Cell>
    <Cell ss:StyleID="s66"><Data ss:Type="String">027346</Data><NamedCell
      ss:Name="_FilterDatabase"/></Cell>
    <Cell ss:StyleID="s68"><Data ss:Type="DateTime">2023-07-25T00:00:00.000</Data><NamedCell
      ss:Name="_FilterDatabase"/></Cell>
    <Cell ss:StyleID="s66"><Data ss:Type="String">Sim</Data><NamedCell
      ss:Name="_FilterDatabase"/></Cell>
    <Cell ss:StyleID="s66"><Data ss:Type="String">006517/01</Data><NamedCell
      ss:Name="_FilterDatabase"/></Cell>
    <Cell ss:StyleID="s67"><Data ss:Type="String">INTEGRADO DISTRIBUIDOR FRIGORIFICO LTDA</Data><NamedCell
      ss:Name="_FilterDatabase"/></Cell>
    <Cell ss:StyleID="s67"><Data ss:Type="String">JD SAO LUIZ</Data><NamedCell
      ss:Name="_FilterDatabase"/></Cell>
    <Cell ss:StyleID="s67"><Data ss:Type="String">14020390</Data><NamedCell
      ss:Name="_FilterDatabase"/></Cell>
    <Cell ss:StyleID="s67"><Data ss:Type="String">RIBEIRAO PRETO</Data><NamedCell
      ss:Name="_FilterDatabase"/></Cell>
    <Cell ss:StyleID="s66"><Data ss:Type="String">SP</Data><NamedCell
      ss:Name="_FilterDatabase"/></Cell>
    <Cell ss:StyleID="s67"><Data ss:Type="String"></Data><NamedCell
      ss:Name="_FilterDatabase"/></Cell>
    <Cell ss:StyleID="s68"><Data ss:Type="DateTime">2023-07-30T00:00:00.000</Data><NamedCell
      ss:Name="_FilterDatabase"/></Cell>
    <Cell ss:StyleID="s68"><Data ss:Type="DateTime">2023-07-31T00:00:00.000</Data><NamedCell
      ss:Name="_FilterDatabase"/></Cell>
    <Cell ss:StyleID="s66"><Data ss:Type="String">FRPTMIFMI000002</Data><NamedCell
      ss:Name="_FilterDatabase"/></Cell>
    <Cell ss:StyleID="s67"><Data ss:Type="String">CORTES CONGELADOS DE FRANGO (FILE DE PEITO INDIVIDUAL) CX PP 18 KG MISTER FRANGO</Data><NamedCell
      ss:Name="_FilterDatabase"/></Cell>
    <Cell ss:StyleID="s76"><Data ss:Type="Number">2160</Data><NamedCell
      ss:Name="_FilterDatabase"/></Cell>
    <Cell ss:StyleID="s69"><Data ss:Type="String">18</Data><NamedCell
      ss:Name="_FilterDatabase"/></Cell>
    <Cell ss:StyleID="s69"><Data ss:Type="String">19.656,00</Data><NamedCell
      ss:Name="_FilterDatabase"/></Cell>
    <Cell ss:StyleID="s66"><Data ss:Type="String"></Data><NamedCell
      ss:Name="_FilterDatabase"/></Cell>
    <Cell ss:StyleID="s66"><Data ss:Type="String"></Data><NamedCell
      ss:Name="_FilterDatabase"/></Cell>
   </Row>
   <Row ss:AutoFitHeight="0">
    <Cell ss:StyleID="s134"><Data ss:Type="String">51</Data><NamedCell
      ss:Name="_FilterDatabase"/></Cell>
    <Cell ss:StyleID="s135"><Data ss:Type="String">000050</Data><NamedCell
      ss:Name="_FilterDatabase"/></Cell>
    <Cell ss:StyleID="s135"><Data ss:Type="String">SARTORATO REPRESENTACOES COMERCIAIS LTDA</Data><NamedCell
      ss:Name="_FilterDatabase"/></Cell>
    <Cell ss:StyleID="s134"><Data ss:Type="String">027448</Data><NamedCell
      ss:Name="_FilterDatabase"/></Cell>
    <Cell ss:StyleID="s136"><Data ss:Type="DateTime">2023-07-28T00:00:00.000</Data><NamedCell
      ss:Name="_FilterDatabase"/></Cell>
    <Cell ss:StyleID="s134"><Data ss:Type="String">SIM</Data><NamedCell
      ss:Name="_FilterDatabase"/></Cell>
    <Cell ss:StyleID="s134"><Data ss:Type="String">035788/01</Data><NamedCell
      ss:Name="_FilterDatabase"/></Cell>
    <Cell ss:StyleID="s135"><Data ss:Type="String">RESOLVE ALIMENTACAO LTDA</Data><NamedCell
      ss:Name="_FilterDatabase"/></Cell>
    <Cell ss:StyleID="s135"><Data ss:Type="String">JARDIM CANADA</Data><NamedCell
      ss:Name="_FilterDatabase"/></Cell>
    <Cell ss:StyleID="s135"><Data ss:Type="String">14024270</Data><NamedCell
      ss:Name="_FilterDatabase"/></Cell>
    <Cell ss:StyleID="s135"><Data ss:Type="String">RIBEIRAO PRETO</Data><NamedCell
      ss:Name="_FilterDatabase"/></Cell>
    <Cell ss:StyleID="s134"><Data ss:Type="String">SP</Data><NamedCell
      ss:Name="_FilterDatabase"/></Cell>
    <Cell ss:StyleID="s135"><Data ss:Type="String">FAVOR FAZER A ENTREGA DESSA NF</Data><NamedCell
      ss:Name="_FilterDatabase"/></Cell>
    <Cell ss:StyleID="s136"><Data ss:Type="DateTime">2023-07-30T00:00:00.000</Data><NamedCell
      ss:Name="_FilterDatabase"/></Cell>
    <Cell ss:StyleID="s136"><Data ss:Type="DateTime">2023-07-31T00:00:00.000</Data><NamedCell
      ss:Name="_FilterDatabase"/></Cell>
    <Cell ss:StyleID="s134"><Data ss:Type="String">FRPTCANMI000033</Data><NamedCell
      ss:Name="_FilterDatabase"/></Cell>
    <Cell ss:StyleID="s135"><Data ss:Type="String">CORTES CONGELADOS DE FRANGO (FILE DE PEITO INDIVIDUAL) CX PP 20 KG (CANCAO ALIMENTOS)</Data><NamedCell
      ss:Name="_FilterDatabase"/></Cell>
    <Cell ss:StyleID="s137"><Data ss:Type="Number">80</Data><NamedCell
      ss:Name="_FilterDatabase"/></Cell>
    <Cell ss:StyleID="s138"><Data ss:Type="String">20</Data><NamedCell
      ss:Name="_FilterDatabase"/></Cell>
    <Cell ss:StyleID="s138"><Data ss:Type="String">744,00</Data><NamedCell
      ss:Name="_FilterDatabase"/></Cell>
    <Cell ss:StyleID="s134"><Data ss:Type="String"></Data><NamedCell
      ss:Name="_FilterDatabase"/></Cell>
    <Cell ss:StyleID="s134"><Data ss:Type="String"></Data><NamedCell
      ss:Name="_FilterDatabase"/></Cell>
   </Row>
   <Row ss:AutoFitHeight="0">
    <Cell ss:StyleID="s140"><Data ss:Type="String">51</Data><NamedCell
      ss:Name="_FilterDatabase"/></Cell>
    <Cell ss:StyleID="s141"><Data ss:Type="String">000050</Data><NamedCell
      ss:Name="_FilterDatabase"/></Cell>
    <Cell ss:StyleID="s141"><Data ss:Type="String">SARTORATO REPRESENTACOES COMERCIAIS LTDA</Data><NamedCell
      ss:Name="_FilterDatabase"/></Cell>
    <Cell ss:StyleID="s140"><Data ss:Type="String">027449</Data><NamedCell
      ss:Name="_FilterDatabase"/></Cell>
    <Cell ss:StyleID="s142"><Data ss:Type="DateTime">2023-07-28T00:00:00.000</Data><NamedCell
      ss:Name="_FilterDatabase"/></Cell>
    <Cell ss:StyleID="s134"><Data ss:Type="String">SIM</Data><NamedCell
      ss:Name="_FilterDatabase"/></Cell>
    <Cell ss:StyleID="s140"><Data ss:Type="String">035788/02</Data><NamedCell
      ss:Name="_FilterDatabase"/></Cell>
    <Cell ss:StyleID="s141"><Data ss:Type="String">RESOLVE ALIMENTACAO LTDA</Data><NamedCell
      ss:Name="_FilterDatabase"/></Cell>
    <Cell ss:StyleID="s141"><Data ss:Type="String">JARDIM CANADA</Data><NamedCell
      ss:Name="_FilterDatabase"/></Cell>
    <Cell ss:StyleID="s141"><Data ss:Type="String">14024270</Data><NamedCell
      ss:Name="_FilterDatabase"/></Cell>
    <Cell ss:StyleID="s141"><Data ss:Type="String">RIBEIRAO PRETO</Data><NamedCell
      ss:Name="_FilterDatabase"/></Cell>
    <Cell ss:StyleID="s140"><Data ss:Type="String">SP</Data><NamedCell
      ss:Name="_FilterDatabase"/></Cell>
    <Cell ss:StyleID="s141"><Data ss:Type="String">FAVOR FAZER A ENTREGA DESSA NF</Data><NamedCell
      ss:Name="_FilterDatabase"/></Cell>
    <Cell ss:StyleID="s142"><Data ss:Type="DateTime">2023-07-30T00:00:00.000</Data><NamedCell
      ss:Name="_FilterDatabase"/></Cell>
    <Cell ss:StyleID="s142"><Data ss:Type="DateTime">2023-07-31T00:00:00.000</Data><NamedCell
      ss:Name="_FilterDatabase"/></Cell>
    <Cell ss:StyleID="s140"><Data ss:Type="String">FRPTCANMI000033</Data><NamedCell
      ss:Name="_FilterDatabase"/></Cell>
    <Cell ss:StyleID="s141"><Data ss:Type="String">CORTES CONGELADOS DE FRANGO (FILE DE PEITO INDIVIDUAL) CX PP 20 KG (CANCAO ALIMENTOS)</Data><NamedCell
      ss:Name="_FilterDatabase"/></Cell>
    <Cell ss:StyleID="s143"><Data ss:Type="Number">100</Data><NamedCell
      ss:Name="_FilterDatabase"/></Cell>
    <Cell ss:StyleID="s144"><Data ss:Type="String">20</Data><NamedCell
      ss:Name="_FilterDatabase"/></Cell>
    <Cell ss:StyleID="s144"><Data ss:Type="String">1.095,60</Data><NamedCell
      ss:Name="_FilterDatabase"/></Cell>
    <Cell ss:StyleID="s140"><Data ss:Type="String"></Data><NamedCell
      ss:Name="_FilterDatabase"/></Cell>
    <Cell ss:StyleID="s140"><Data ss:Type="String"></Data><NamedCell
      ss:Name="_FilterDatabase"/></Cell>
   </Row>
   <Row ss:AutoFitHeight="0">
    <Cell ss:StyleID="s134"><Data ss:Type="String">51</Data><NamedCell
      ss:Name="_FilterDatabase"/></Cell>
    <Cell ss:StyleID="s135"><Data ss:Type="String">000050</Data><NamedCell
      ss:Name="_FilterDatabase"/></Cell>
    <Cell ss:StyleID="s135"><Data ss:Type="String">SARTORATO REPRESENTACOES COMERCIAIS LTDA</Data><NamedCell
      ss:Name="_FilterDatabase"/></Cell>
    <Cell ss:StyleID="s134"><Data ss:Type="String">027449</Data><NamedCell
      ss:Name="_FilterDatabase"/></Cell>
    <Cell ss:StyleID="s136"><Data ss:Type="DateTime">2023-07-28T00:00:00.000</Data><NamedCell
      ss:Name="_FilterDatabase"/></Cell>
    <Cell ss:StyleID="s134"><Data ss:Type="String">SIM</Data><NamedCell
      ss:Name="_FilterDatabase"/></Cell>
    <Cell ss:StyleID="s140"><Data ss:Type="String">035788/02</Data><NamedCell
      ss:Name="_FilterDatabase"/></Cell>
    <Cell ss:StyleID="s135"><Data ss:Type="String">RESOLVE ALIMENTACAO LTDA</Data><NamedCell
      ss:Name="_FilterDatabase"/></Cell>
    <Cell ss:StyleID="s135"><Data ss:Type="String">JARDIM CANADA</Data><NamedCell
      ss:Name="_FilterDatabase"/></Cell>
    <Cell ss:StyleID="s135"><Data ss:Type="String">14024270</Data><NamedCell
      ss:Name="_FilterDatabase"/></Cell>
    <Cell ss:StyleID="s135"><Data ss:Type="String">RIBEIRAO PRETO</Data><NamedCell
      ss:Name="_FilterDatabase"/></Cell>
    <Cell ss:StyleID="s134"><Data ss:Type="String">SP</Data><NamedCell
      ss:Name="_FilterDatabase"/></Cell>
    <Cell ss:StyleID="s135"><Data ss:Type="String">FAVOR FAZER A ENTREGA DESSA NF</Data><NamedCell
      ss:Name="_FilterDatabase"/></Cell>
    <Cell ss:StyleID="s136"><Data ss:Type="DateTime">2023-07-30T00:00:00.000</Data><NamedCell
      ss:Name="_FilterDatabase"/></Cell>
    <Cell ss:StyleID="s136"><Data ss:Type="DateTime">2023-07-31T00:00:00.000</Data><NamedCell
      ss:Name="_FilterDatabase"/></Cell>
    <Cell ss:StyleID="s134"><Data ss:Type="String">FRPTMIFMI000008</Data><NamedCell
      ss:Name="_FilterDatabase"/></Cell>
    <Cell ss:StyleID="s135"><Data ss:Type="String">CORTES CONGELADO DE FRANGO (FILEZINHO SASSAMI) PCT 6 KG CX PP 18 KG (MISTER FRANGO)</Data><NamedCell
      ss:Name="_FilterDatabase"/></Cell>
    <Cell ss:StyleID="s137"><Data ss:Type="Number">18</Data><NamedCell
      ss:Name="_FilterDatabase"/></Cell>
    <Cell ss:StyleID="s138"><Data ss:Type="String">18</Data><NamedCell
      ss:Name="_FilterDatabase"/></Cell>
    <Cell ss:StyleID="s138"><Data ss:Type="String">1.095,60</Data><NamedCell
      ss:Name="_FilterDatabase"/></Cell>
    <Cell ss:StyleID="s134"><Data ss:Type="String"></Data><NamedCell
      ss:Name="_FilterDatabase"/></Cell>
    <Cell ss:StyleID="s134"><Data ss:Type="String"></Data><NamedCell
      ss:Name="_FilterDatabase"/></Cell>
   </Row>
   <Row ss:AutoFitHeight="0">
    <Cell ss:StyleID="s140"><Data ss:Type="String">51</Data><NamedCell
      ss:Name="_FilterDatabase"/></Cell>
    <Cell ss:StyleID="s141"><Data ss:Type="String">000050</Data><NamedCell
      ss:Name="_FilterDatabase"/></Cell>
    <Cell ss:StyleID="s141"><Data ss:Type="String">SARTORATO REPRESENTACOES COMERCIAIS LTDA</Data><NamedCell
      ss:Name="_FilterDatabase"/></Cell>
    <Cell ss:StyleID="s140"><Data ss:Type="String">027450</Data><NamedCell
      ss:Name="_FilterDatabase"/></Cell>
    <Cell ss:StyleID="s142"><Data ss:Type="DateTime">2023-07-28T00:00:00.000</Data><NamedCell
      ss:Name="_FilterDatabase"/></Cell>
    <Cell ss:StyleID="s134"><Data ss:Type="String">SIM</Data><NamedCell
      ss:Name="_FilterDatabase"/></Cell>
    <Cell ss:StyleID="s140"><Data ss:Type="String">035788/03</Data><NamedCell
      ss:Name="_FilterDatabase"/></Cell>
    <Cell ss:StyleID="s141"><Data ss:Type="String">RESOLVE ALIMENTACAO LTDA</Data><NamedCell
      ss:Name="_FilterDatabase"/></Cell>
    <Cell ss:StyleID="s141"><Data ss:Type="String">JARDIM CANADA</Data><NamedCell
      ss:Name="_FilterDatabase"/></Cell>
    <Cell ss:StyleID="s141"><Data ss:Type="String">14024270</Data><NamedCell
      ss:Name="_FilterDatabase"/></Cell>
    <Cell ss:StyleID="s141"><Data ss:Type="String">RIBEIRAO PRETO</Data><NamedCell
      ss:Name="_FilterDatabase"/></Cell>
    <Cell ss:StyleID="s140"><Data ss:Type="String">SP</Data><NamedCell
      ss:Name="_FilterDatabase"/></Cell>
    <Cell ss:StyleID="s141"><Data ss:Type="String">FAVOR FAZER A ENTREGA DESSA NF</Data><NamedCell
      ss:Name="_FilterDatabase"/></Cell>
    <Cell ss:StyleID="s142"><Data ss:Type="DateTime">2023-07-30T00:00:00.000</Data><NamedCell
      ss:Name="_FilterDatabase"/></Cell>
    <Cell ss:StyleID="s142"><Data ss:Type="DateTime">2023-07-31T00:00:00.000</Data><NamedCell
      ss:Name="_FilterDatabase"/></Cell>
    <Cell ss:StyleID="s140"><Data ss:Type="String">FRPTCANMI000033</Data><NamedCell
      ss:Name="_FilterDatabase"/></Cell>
    <Cell ss:StyleID="s141"><Data ss:Type="String">CORTES CONGELADOS DE FRANGO (FILE DE PEITO INDIVIDUAL) CX PP 20 KG (CANCAO ALIMENTOS)</Data><NamedCell
      ss:Name="_FilterDatabase"/></Cell>
    <Cell ss:StyleID="s143"><Data ss:Type="Number">60</Data><NamedCell
      ss:Name="_FilterDatabase"/></Cell>
    <Cell ss:StyleID="s144"><Data ss:Type="String">20</Data><NamedCell
      ss:Name="_FilterDatabase"/></Cell>
    <Cell ss:StyleID="s144"><Data ss:Type="String">558,00</Data><NamedCell
      ss:Name="_FilterDatabase"/></Cell>
    <Cell ss:StyleID="s140"><Data ss:Type="String"></Data><NamedCell
      ss:Name="_FilterDatabase"/></Cell>
    <Cell ss:StyleID="s140"><Data ss:Type="String"></Data><NamedCell
      ss:Name="_FilterDatabase"/></Cell>
   </Row>
   <Row ss:AutoFitHeight="0">
    <Cell ss:StyleID="s134"><Data ss:Type="String">51</Data><NamedCell
      ss:Name="_FilterDatabase"/></Cell>
    <Cell ss:StyleID="s135"><Data ss:Type="String">000050</Data><NamedCell
      ss:Name="_FilterDatabase"/></Cell>
    <Cell ss:StyleID="s135"><Data ss:Type="String">SARTORATO REPRESENTACOES COMERCIAIS LTDA</Data><NamedCell
      ss:Name="_FilterDatabase"/></Cell>
    <Cell ss:StyleID="s134"><Data ss:Type="String">027451</Data><NamedCell
      ss:Name="_FilterDatabase"/></Cell>
    <Cell ss:StyleID="s136"><Data ss:Type="DateTime">2023-07-28T00:00:00.000</Data><NamedCell
      ss:Name="_FilterDatabase"/></Cell>
    <Cell ss:StyleID="s134"><Data ss:Type="String">SIM</Data><NamedCell
      ss:Name="_FilterDatabase"/></Cell>
    <Cell ss:StyleID="s134"><Data ss:Type="String">035788/05</Data><NamedCell
      ss:Name="_FilterDatabase"/></Cell>
    <Cell ss:StyleID="s135"><Data ss:Type="String">RESOLVE ALIMENTACAO LTDA</Data><NamedCell
      ss:Name="_FilterDatabase"/></Cell>
    <Cell ss:StyleID="s135"><Data ss:Type="String">JARDIM CANADA</Data><NamedCell
      ss:Name="_FilterDatabase"/></Cell>
    <Cell ss:StyleID="s135"><Data ss:Type="String">14024270</Data><NamedCell
      ss:Name="_FilterDatabase"/></Cell>
    <Cell ss:StyleID="s135"><Data ss:Type="String">RIBEIRAO PRETO</Data><NamedCell
      ss:Name="_FilterDatabase"/></Cell>
    <Cell ss:StyleID="s134"><Data ss:Type="String">SP</Data><NamedCell
      ss:Name="_FilterDatabase"/></Cell>
    <Cell ss:StyleID="s135"><Data ss:Type="String">FAVOR FAZER A ENTREGA DESSA NF</Data><NamedCell
      ss:Name="_FilterDatabase"/></Cell>
    <Cell ss:StyleID="s136"><Data ss:Type="DateTime">2023-07-30T00:00:00.000</Data><NamedCell
      ss:Name="_FilterDatabase"/></Cell>
    <Cell ss:StyleID="s136"><Data ss:Type="DateTime">2023-07-31T00:00:00.000</Data><NamedCell
      ss:Name="_FilterDatabase"/></Cell>
    <Cell ss:StyleID="s134"><Data ss:Type="String">FRPTCANMI000033</Data><NamedCell
      ss:Name="_FilterDatabase"/></Cell>
    <Cell ss:StyleID="s135"><Data ss:Type="String">CORTES CONGELADOS DE FRANGO (FILE DE PEITO INDIVIDUAL) CX PP 20 KG (CANCAO ALIMENTOS)</Data><NamedCell
      ss:Name="_FilterDatabase"/></Cell>
    <Cell ss:StyleID="s137"><Data ss:Type="Number">280</Data><NamedCell
      ss:Name="_FilterDatabase"/></Cell>
    <Cell ss:StyleID="s138"><Data ss:Type="String">20</Data><NamedCell
      ss:Name="_FilterDatabase"/></Cell>
    <Cell ss:StyleID="s138"><Data ss:Type="String">2.604,00</Data><NamedCell
      ss:Name="_FilterDatabase"/></Cell>
    <Cell ss:StyleID="s134"><Data ss:Type="String"></Data><NamedCell
      ss:Name="_FilterDatabase"/></Cell>
    <Cell ss:StyleID="s134"><Data ss:Type="String"></Data><NamedCell
      ss:Name="_FilterDatabase"/></Cell>
   </Row>
   <Row ss:AutoFitHeight="0">
    <Cell ss:StyleID="s140"><Data ss:Type="String">51</Data><NamedCell
      ss:Name="_FilterDatabase"/></Cell>
    <Cell ss:StyleID="s141"><Data ss:Type="String">000050</Data><NamedCell
      ss:Name="_FilterDatabase"/></Cell>
    <Cell ss:StyleID="s141"><Data ss:Type="String">SARTORATO REPRESENTACOES COMERCIAIS LTDA</Data><NamedCell
      ss:Name="_FilterDatabase"/></Cell>
    <Cell ss:StyleID="s140"><Data ss:Type="String">027452</Data><NamedCell
      ss:Name="_FilterDatabase"/></Cell>
    <Cell ss:StyleID="s142"><Data ss:Type="DateTime">2023-07-28T00:00:00.000</Data><NamedCell
      ss:Name="_FilterDatabase"/></Cell>
    <Cell ss:StyleID="s134"><Data ss:Type="String">SIM</Data><NamedCell
      ss:Name="_FilterDatabase"/></Cell>
    <Cell ss:StyleID="s140"><Data ss:Type="String">035788/06</Data><NamedCell
      ss:Name="_FilterDatabase"/></Cell>
    <Cell ss:StyleID="s141"><Data ss:Type="String">RESOLVE ALIMENTACAO LTDA</Data><NamedCell
      ss:Name="_FilterDatabase"/></Cell>
    <Cell ss:StyleID="s141"><Data ss:Type="String">JARDIM CANADA</Data><NamedCell
      ss:Name="_FilterDatabase"/></Cell>
    <Cell ss:StyleID="s141"><Data ss:Type="String">14024270</Data><NamedCell
      ss:Name="_FilterDatabase"/></Cell>
    <Cell ss:StyleID="s141"><Data ss:Type="String">RIBEIRAO PRETO</Data><NamedCell
      ss:Name="_FilterDatabase"/></Cell>
    <Cell ss:StyleID="s140"><Data ss:Type="String">SP</Data><NamedCell
      ss:Name="_FilterDatabase"/></Cell>
    <Cell ss:StyleID="s141"><Data ss:Type="String">FAVOR FAZER A ENTREGA DESSA NF</Data><NamedCell
      ss:Name="_FilterDatabase"/></Cell>
    <Cell ss:StyleID="s142"><Data ss:Type="DateTime">2023-07-30T00:00:00.000</Data><NamedCell
      ss:Name="_FilterDatabase"/></Cell>
    <Cell ss:StyleID="s142"><Data ss:Type="DateTime">2023-07-31T00:00:00.000</Data><NamedCell
      ss:Name="_FilterDatabase"/></Cell>
    <Cell ss:StyleID="s140"><Data ss:Type="String">FRPTCANMI000033</Data><NamedCell
      ss:Name="_FilterDatabase"/></Cell>
    <Cell ss:StyleID="s141"><Data ss:Type="String">CORTES CONGELADOS DE FRANGO (FILE DE PEITO INDIVIDUAL) CX PP 20 KG (CANCAO ALIMENTOS)</Data><NamedCell
      ss:Name="_FilterDatabase"/></Cell>
    <Cell ss:StyleID="s143"><Data ss:Type="Number">80</Data><NamedCell
      ss:Name="_FilterDatabase"/></Cell>
    <Cell ss:StyleID="s144"><Data ss:Type="String">20</Data><NamedCell
      ss:Name="_FilterDatabase"/></Cell>
    <Cell ss:StyleID="s144"><Data ss:Type="String">744,00</Data><NamedCell
      ss:Name="_FilterDatabase"/></Cell>
    <Cell ss:StyleID="s140"><Data ss:Type="String"></Data><NamedCell
      ss:Name="_FilterDatabase"/></Cell>
    <Cell ss:StyleID="s140"><Data ss:Type="String"></Data><NamedCell
      ss:Name="_FilterDatabase"/></Cell>
   </Row>
   <Row ss:AutoFitHeight="0">
    <Cell ss:StyleID="s134"><Data ss:Type="String">51</Data><NamedCell
      ss:Name="_FilterDatabase"/></Cell>
    <Cell ss:StyleID="s135"><Data ss:Type="String">000050</Data><NamedCell
      ss:Name="_FilterDatabase"/></Cell>
    <Cell ss:StyleID="s135"><Data ss:Type="String">SARTORATO REPRESENTACOES COMERCIAIS LTDA</Data><NamedCell
      ss:Name="_FilterDatabase"/></Cell>
    <Cell ss:StyleID="s134"><Data ss:Type="String">027453</Data><NamedCell
      ss:Name="_FilterDatabase"/></Cell>
    <Cell ss:StyleID="s136"><Data ss:Type="DateTime">2023-07-28T00:00:00.000</Data><NamedCell
      ss:Name="_FilterDatabase"/></Cell>
    <Cell ss:StyleID="s134"><Data ss:Type="String">SIM</Data><NamedCell
      ss:Name="_FilterDatabase"/></Cell>
    <Cell ss:StyleID="s134"><Data ss:Type="String">035788/07</Data><NamedCell
      ss:Name="_FilterDatabase"/></Cell>
    <Cell ss:StyleID="s135"><Data ss:Type="String">RESOLVE ALIMENTACAO LTDA</Data><NamedCell
      ss:Name="_FilterDatabase"/></Cell>
    <Cell ss:StyleID="s135"><Data ss:Type="String">JARDIM CANADA</Data><NamedCell
      ss:Name="_FilterDatabase"/></Cell>
    <Cell ss:StyleID="s135"><Data ss:Type="String">14024270</Data><NamedCell
      ss:Name="_FilterDatabase"/></Cell>
    <Cell ss:StyleID="s135"><Data ss:Type="String">RIBEIRAO PRETO</Data><NamedCell
      ss:Name="_FilterDatabase"/></Cell>
    <Cell ss:StyleID="s134"><Data ss:Type="String">SP</Data><NamedCell
      ss:Name="_FilterDatabase"/></Cell>
    <Cell ss:StyleID="s135"><Data ss:Type="String">FAVOR FAZER A ENTREGA DESSA NF</Data><NamedCell
      ss:Name="_FilterDatabase"/></Cell>
    <Cell ss:StyleID="s136"><Data ss:Type="DateTime">2023-07-30T00:00:00.000</Data><NamedCell
      ss:Name="_FilterDatabase"/></Cell>
    <Cell ss:StyleID="s136"><Data ss:Type="DateTime">2023-07-31T00:00:00.000</Data><NamedCell
      ss:Name="_FilterDatabase"/></Cell>
    <Cell ss:StyleID="s134"><Data ss:Type="String">FRPTCANMI000033</Data><NamedCell
      ss:Name="_FilterDatabase"/></Cell>
    <Cell ss:StyleID="s135"><Data ss:Type="String">CORTES CONGELADOS DE FRANGO (FILE DE PEITO INDIVIDUAL) CX PP 20 KG (CANCAO ALIMENTOS)</Data><NamedCell
      ss:Name="_FilterDatabase"/></Cell>
    <Cell ss:StyleID="s137"><Data ss:Type="Number">180</Data><NamedCell
      ss:Name="_FilterDatabase"/></Cell>
    <Cell ss:StyleID="s138"><Data ss:Type="String">20</Data><NamedCell
      ss:Name="_FilterDatabase"/></Cell>
    <Cell ss:StyleID="s138"><Data ss:Type="String">1.674,00</Data><NamedCell
      ss:Name="_FilterDatabase"/></Cell>
    <Cell ss:StyleID="s134"><Data ss:Type="String"></Data><NamedCell
      ss:Name="_FilterDatabase"/></Cell>
    <Cell ss:StyleID="s134"><Data ss:Type="String"></Data><NamedCell
      ss:Name="_FilterDatabase"/></Cell>
   </Row>
   <Row ss:AutoFitHeight="0">
    <Cell ss:StyleID="s140"><Data ss:Type="String">51</Data><NamedCell
      ss:Name="_FilterDatabase"/></Cell>
    <Cell ss:StyleID="s141"><Data ss:Type="String">000050</Data><NamedCell
      ss:Name="_FilterDatabase"/></Cell>
    <Cell ss:StyleID="s141"><Data ss:Type="String">SARTORATO REPRESENTACOES COMERCIAIS LTDA</Data><NamedCell
      ss:Name="_FilterDatabase"/></Cell>
    <Cell ss:StyleID="s140"><Data ss:Type="String">027454</Data><NamedCell
      ss:Name="_FilterDatabase"/></Cell>
    <Cell ss:StyleID="s142"><Data ss:Type="DateTime">2023-07-28T00:00:00.000</Data><NamedCell
      ss:Name="_FilterDatabase"/></Cell>
    <Cell ss:StyleID="s134"><Data ss:Type="String">SIM</Data><NamedCell
      ss:Name="_FilterDatabase"/></Cell>
    <Cell ss:StyleID="s140"><Data ss:Type="String">035788/04</Data><NamedCell
      ss:Name="_FilterDatabase"/></Cell>
    <Cell ss:StyleID="s141"><Data ss:Type="String">RESOLVE ALIMENTACAO LTDA</Data><NamedCell
      ss:Name="_FilterDatabase"/></Cell>
    <Cell ss:StyleID="s141"><Data ss:Type="String">JARDIM CANADA</Data><NamedCell
      ss:Name="_FilterDatabase"/></Cell>
    <Cell ss:StyleID="s141"><Data ss:Type="String">14024270</Data><NamedCell
      ss:Name="_FilterDatabase"/></Cell>
    <Cell ss:StyleID="s141"><Data ss:Type="String">RIBEIRAO PRETO</Data><NamedCell
      ss:Name="_FilterDatabase"/></Cell>
    <Cell ss:StyleID="s140"><Data ss:Type="String">SP</Data><NamedCell
      ss:Name="_FilterDatabase"/></Cell>
    <Cell ss:StyleID="s141"><Data ss:Type="String">FAVOR FAZER A ENTREGA DESSA NF</Data><NamedCell
      ss:Name="_FilterDatabase"/></Cell>
    <Cell ss:StyleID="s142"><Data ss:Type="DateTime">2023-07-30T00:00:00.000</Data><NamedCell
      ss:Name="_FilterDatabase"/></Cell>
    <Cell ss:StyleID="s142"><Data ss:Type="DateTime">2023-07-31T00:00:00.000</Data><NamedCell
      ss:Name="_FilterDatabase"/></Cell>
    <Cell ss:StyleID="s140"><Data ss:Type="String">FRCSCANMI000019</Data><NamedCell
      ss:Name="_FilterDatabase"/></Cell>
    <Cell ss:StyleID="s141"><Data ss:Type="String">CORTE CONGELADO DE FRANGO (COXA/SOBRECOXA S/OSSO) CX PP 18KG SIF 4166 (CANCAO)</Data><NamedCell
      ss:Name="_FilterDatabase"/></Cell>
    <Cell ss:StyleID="s143"><Data ss:Type="Number">18</Data><NamedCell
      ss:Name="_FilterDatabase"/></Cell>
    <Cell ss:StyleID="s144"><Data ss:Type="String">18</Data><NamedCell
      ss:Name="_FilterDatabase"/></Cell>
    <Cell ss:StyleID="s144"><Data ss:Type="String">1.469,40</Data><NamedCell
      ss:Name="_FilterDatabase"/></Cell>
    <Cell ss:StyleID="s140"><Data ss:Type="String"></Data><NamedCell
      ss:Name="_FilterDatabase"/></Cell>
    <Cell ss:StyleID="s140"><Data ss:Type="String"></Data><NamedCell
      ss:Name="_FilterDatabase"/></Cell>
   </Row>
   <Row ss:AutoFitHeight="0">
    <Cell ss:StyleID="s134"><Data ss:Type="String">51</Data><NamedCell
      ss:Name="_FilterDatabase"/></Cell>
    <Cell ss:StyleID="s135"><Data ss:Type="String">000050</Data><NamedCell
      ss:Name="_FilterDatabase"/></Cell>
    <Cell ss:StyleID="s135"><Data ss:Type="String">SARTORATO REPRESENTACOES COMERCIAIS LTDA</Data><NamedCell
      ss:Name="_FilterDatabase"/></Cell>
    <Cell ss:StyleID="s134"><Data ss:Type="String">027454</Data><NamedCell
      ss:Name="_FilterDatabase"/></Cell>
    <Cell ss:StyleID="s136"><Data ss:Type="DateTime">2023-07-28T00:00:00.000</Data><NamedCell
      ss:Name="_FilterDatabase"/></Cell>
    <Cell ss:StyleID="s134"><Data ss:Type="String">SIM</Data><NamedCell
      ss:Name="_FilterDatabase"/></Cell>
    <Cell ss:StyleID="s134"><Data ss:Type="String">035788/04</Data><NamedCell
      ss:Name="_FilterDatabase"/></Cell>
    <Cell ss:StyleID="s135"><Data ss:Type="String">RESOLVE ALIMENTACAO LTDA</Data><NamedCell
      ss:Name="_FilterDatabase"/></Cell>
    <Cell ss:StyleID="s135"><Data ss:Type="String">JARDIM CANADA</Data><NamedCell
      ss:Name="_FilterDatabase"/></Cell>
    <Cell ss:StyleID="s135"><Data ss:Type="String">14024270</Data><NamedCell
      ss:Name="_FilterDatabase"/></Cell>
    <Cell ss:StyleID="s135"><Data ss:Type="String">RIBEIRAO PRETO</Data><NamedCell
      ss:Name="_FilterDatabase"/></Cell>
    <Cell ss:StyleID="s134"><Data ss:Type="String">SP</Data><NamedCell
      ss:Name="_FilterDatabase"/></Cell>
    <Cell ss:StyleID="s135"><Data ss:Type="String">FAVOR FAZER A ENTREGA DESSA NF</Data><NamedCell
      ss:Name="_FilterDatabase"/></Cell>
    <Cell ss:StyleID="s136"><Data ss:Type="DateTime">2023-07-30T00:00:00.000</Data><NamedCell
      ss:Name="_FilterDatabase"/></Cell>
    <Cell ss:StyleID="s136"><Data ss:Type="DateTime">2023-07-31T00:00:00.000</Data><NamedCell
      ss:Name="_FilterDatabase"/></Cell>
    <Cell ss:StyleID="s134"><Data ss:Type="String">FRPTCANMI000033</Data><NamedCell
      ss:Name="_FilterDatabase"/></Cell>
    <Cell ss:StyleID="s135"><Data ss:Type="String">CORTES CONGELADOS DE FRANGO (FILE DE PEITO INDIVIDUAL) CX PP 20 KG (CANCAO ALIMENTOS)</Data><NamedCell
      ss:Name="_FilterDatabase"/></Cell>
    <Cell ss:StyleID="s137"><Data ss:Type="Number">140</Data><NamedCell
      ss:Name="_FilterDatabase"/></Cell>
    <Cell ss:StyleID="s138"><Data ss:Type="String">20</Data><NamedCell
      ss:Name="_FilterDatabase"/></Cell>
    <Cell ss:StyleID="s138"><Data ss:Type="String">1.469,40</Data><NamedCell
      ss:Name="_FilterDatabase"/></Cell>
    <Cell ss:StyleID="s134"><Data ss:Type="String"></Data><NamedCell
      ss:Name="_FilterDatabase"/></Cell>
    <Cell ss:StyleID="s134"><Data ss:Type="String"></Data><NamedCell
      ss:Name="_FilterDatabase"/></Cell>
   </Row>
   <Row ss:AutoFitHeight="0">
    <Cell ss:StyleID="s70"><Data ss:Type="String">51</Data><NamedCell
      ss:Name="_FilterDatabase"/></Cell>
    <Cell ss:StyleID="s71"><Data ss:Type="String">000254</Data><NamedCell
      ss:Name="_FilterDatabase"/></Cell>
    <Cell ss:StyleID="s71"><Data ss:Type="String">CRIATHIV REPRESENTACOES COMERCIAIS LTDA</Data><NamedCell
      ss:Name="_FilterDatabase"/></Cell>
    <Cell ss:StyleID="s70"><Data ss:Type="String">027405</Data><NamedCell
      ss:Name="_FilterDatabase"/></Cell>
    <Cell ss:StyleID="s72"><Data ss:Type="DateTime">2023-07-26T00:00:00.000</Data><NamedCell
      ss:Name="_FilterDatabase"/></Cell>
    <Cell ss:StyleID="s70"><Data ss:Type="String">Sim</Data><NamedCell
      ss:Name="_FilterDatabase"/></Cell>
    <Cell ss:StyleID="s70"><Data ss:Type="String">023318/01</Data><NamedCell
      ss:Name="_FilterDatabase"/></Cell>
    <Cell ss:StyleID="s71"><Data ss:Type="String">BISPO DISTRIBUIDORA DE PRODUTOS ALIMENTICIOS EIRELI</Data><NamedCell
      ss:Name="_FilterDatabase"/></Cell>
    <Cell ss:StyleID="s71"><Data ss:Type="String">BOA VISTA DOS CASTILHOS</Data><NamedCell
      ss:Name="_FilterDatabase"/></Cell>
    <Cell ss:StyleID="s71"><Data ss:Type="String">15200000</Data><NamedCell
      ss:Name="_FilterDatabase"/></Cell>
    <Cell ss:StyleID="s71"><Data ss:Type="String">JOSE BONIFACIO</Data><NamedCell
      ss:Name="_FilterDatabase"/></Cell>
    <Cell ss:StyleID="s70"><Data ss:Type="String">SP</Data><NamedCell
      ss:Name="_FilterDatabase"/></Cell>
    <Cell ss:StyleID="s71"><Data ss:Type="String"></Data><NamedCell
      ss:Name="_FilterDatabase"/></Cell>
    <Cell ss:StyleID="s72"><Data ss:Type="DateTime">2023-07-27T00:00:00.000</Data><NamedCell
      ss:Name="_FilterDatabase"/></Cell>
    <Cell ss:StyleID="s72"><Data ss:Type="DateTime">2023-07-28T00:00:00.000</Data><NamedCell
      ss:Name="_FilterDatabase"/></Cell>
    <Cell ss:StyleID="s70"><Data ss:Type="String">FRPTMIFMI000008</Data><NamedCell
      ss:Name="_FilterDatabase"/></Cell>
    <Cell ss:StyleID="s71"><Data ss:Type="String">CORTES CONGELADO DE FRANGO (FILEZINHO SASSAMI) PCT 6 KG CX PP 18 KG (MISTER FRANGO)</Data><NamedCell
      ss:Name="_FilterDatabase"/></Cell>
    <Cell ss:StyleID="s77"><Data ss:Type="Number">2340</Data><NamedCell
      ss:Name="_FilterDatabase"/></Cell>
    <Cell ss:StyleID="s73"><Data ss:Type="String">18</Data><NamedCell
      ss:Name="_FilterDatabase"/></Cell>
    <Cell ss:StyleID="s73"><Data ss:Type="String">21.294,00</Data><NamedCell
      ss:Name="_FilterDatabase"/></Cell>
    <Cell ss:StyleID="s70"><Data ss:Type="String"></Data><NamedCell
      ss:Name="_FilterDatabase"/></Cell>
    <Cell ss:StyleID="s70"><Data ss:Type="String"></Data><NamedCell
      ss:Name="_FilterDatabase"/></Cell>
   </Row>
  </Table>
  <WorksheetOptions xmlns="urn:schemas-microsoft-com:office:excel">
   <PageSetup>
    <Header x:Margin="0.31496062000000002"/>
    <Footer x:Margin="0.31496062000000002"/>
    <PageMargins x:Bottom="0.78740157499999996" x:Left="0.511811024"
     x:Right="0.511811024" x:Top="0.78740157499999996"/>
   </PageSetup>
   <Unsynced/>
   <Selected/>
   <Panes>
    <Pane>
     <Number>3</Number>
     <ActiveRow>13</ActiveRow>
     <ActiveCol>21</ActiveCol>
     <RangeSelection>R1C1:R14C22</RangeSelection>
    </Pane>
   </Panes>
   <ProtectObjects>False</ProtectObjects>
   <ProtectScenarios>False</ProtectScenarios>
  </WorksheetOptions>
  <AutoFilter x:Range="R1C1:R18C22"
   xmlns="urn:schemas-microsoft-com:office:excel">
  </AutoFilter>
 </Worksheet>
</Workbook>
